setup.py
BMKR/__init__.py
BMKR/data_loader.py
BMKR/data_utils.py
BMKR/graph.py
BMKR/graph_utils.py
BMKR/layers.py
BMKR/lsh.py
BMKR/main.py
BMKR/model.py
BMKR/preprocess.py
BMKR/train.py
BMKR/uiprocess.py
BMKR/uitrain.py
BMKR.egg-info/PKG-INFO
BMKR.egg-info/SOURCES.txt
BMKR.egg-info/dependency_links.txt
BMKR.egg-info/top_level.txt
BMKR.egg-info/zip-safe
BMKR/data/book/item_embeddings.dat
BMKR/data/book/rating_test.dat
BMKR/data/book/rating_train.dat
BMKR/data/book/ratings_final.dat
BMKR/data/book/user_embeddings.dat
BMKR/data/book1/rating_test.dat
BMKR/data/book1/rating_train.dat
BMKR/data/movie/item_embeddings.dat
BMKR/data/movie/ratings.dat
BMKR/data/movie/user_embeddings.dat
BMKR/data/movie-1230/item_embeddings.dat
BMKR/data/movie-1230/user_embeddings.dat
BMKR/data/movie-2400/item_embeddings.dat
BMKR/data/movie-2400/user_embeddings.dat
BMKR/data/movie-3600/item_embeddings.dat
BMKR/data/movie-3600/user_embeddings.dat
BMKR/data/music/head_embeddings.dat
BMKR/data/music/item_embeddings.dat
BMKR/data/music/rating_test.dat
BMKR/data/music/rating_train.dat
BMKR/data/music/tail_embeddings.dat
BMKR/data/music/user_artists.dat
BMKR/data/music/user_embeddings.dat
BMKR/data/music/vectors_u.dat
BMKR/data/music/vectors_v.dat